refpy/__init__.py
refpy/abaqus_tools.py
refpy/dnv_tools.py
refpy/lateral_buckling_tools.py
refpy/linepipe_tools.py
refpy/oos_tools.py
refpy/pipe_soil_interaction_tools.py
refpy-0.1.26.dist-info/licenses/LICENSE
refpy-0.1.26.dist-info/METADATA
refpy-0.1.26.dist-info/WHEEL
refpy-0.1.26.dist-info/top_level.txt
refpy-0.1.26.dist-info/RECORD
