Metadata-Version: 2.4
Name: refpy
Version: 0.1.26
Summary: Package for subsea pipelines and risers design in Python
Home-page: https://github.com/refpy/refpy
Author: ismael-ripoll
License: MIT License
Project-URL: Documentation, https://refpy.github.io/refpy
Project-URL: Source, https://github.com/refpy/refpy
Project-URL: Tracker, https://github.com/refpy/refpy/issues
Classifier: Programming Language :: Python :: 3
Classifier: License :: OSI Approved :: MIT License
Classifier: Operating System :: OS Independent
Requires-Python: >=3.10
License-File: LICENSE
Dynamic: author
Dynamic: classifier
Dynamic: description
Dynamic: description-content-type
Dynamic: home-page
Dynamic: license
Dynamic: license-file
Dynamic: project-url
Dynamic: requires-python
Dynamic: summary
